{
  "dev": {
    "awscloudformation": {
      "AuthRoleName": "amplify-myapp-dev-44405-authRole",
      "UnauthRoleArn": "arn:aws:iam::266735802934:role/amplify-myapp-dev-44405-unauthRole",
      "AuthRoleArn": "arn:aws:iam::266735802934:role/amplify-myapp-dev-44405-authRole",
      "Region": "ap-northeast-1",
      "DeploymentBucketName": "amplify-myapp-dev-44405-deployment",
      "UnauthRoleName": "amplify-myapp-dev-44405-unauthRole",
      "StackName": "amplify-myapp-dev-44405",
      "StackId": "arn:aws:cloudformation:ap-northeast-1:266735802934:stack/amplify-myapp-dev-44405/c063ce00-0426-11f0-9cc7-0ab8e7d0bd79",
      "AmplifyAppId": "d2wfsb351iqis3"
    },
    "categories": {
      "auth": {
        "myappbba0a127": {}
      },
      "function": {
        "S3Trigger0308eca7": {
          "deploymentBucketName": "amplify-myapp-dev-44405-deployment",
          "s3Key": "amplify-builds/S3Trigger0308eca7-5042354c4e7955744436-build.zip",
          "rdsHost": "database-1.czmmgmk2enga.ap-northeast-1.rds.amazonaws.com",
          "rdsUser": "admin",
          "rdsPassword": "MToKGR4hBoQzhKXUCuxO",
          "rdsDatabase": "myapp-rds"
        },
        "rdsLambdaFunction": {
          "deploymentBucketName": "amplify-myapp-dev-44405-deployment",
          "s3Key": "amplify-builds/rdsLambdaFunction-3845774c6a7a555a6363-build.zip",
          "rdsHost": "database-1.czmmgmk2enga.ap-northeast-1.rds.amazonaws.com",
          "rdsUser": "admin",
          "rdsPassword": "MToKGR4hBoQzhKXUCuxO",
          "rdsDatabase": "database-1"
        }
      },
      "storage": {
        "s38d7558c4": {}
      },
      "api": {
        "myapp": {}
      }
    }
  }
}